py23/__init__.py
py23-1.2.dist-info/LICENSE
py23-1.2.dist-info/METADATA
py23-1.2.dist-info/WHEEL
py23-1.2.dist-info/top_level.txt
py23-1.2.dist-info/RECORD
