Metadata-Version: 2.1
Name: py23
Version: 1.2
Summary: Python 2/3 compatible functions pack
Home-page: https://github.com/vb64/py23
Author: Vitaly Bogomolov
Author-email: mail@vitaly-bogomolov.ru
License: UNKNOWN
Project-URL: Bug Tracker, https://github.com/vb64/py23/issues
Platform: UNKNOWN
Classifier: Programming Language :: Python
Classifier: License :: OSI Approved :: MIT License
Classifier: Operating System :: OS Independent
